rkmath/__init__.py
rkmath/myfunctions.py
rkmath-0.2.9.dist-info/licenses/LICENSE
rkmath-0.2.9.dist-info/METADATA
rkmath-0.2.9.dist-info/WHEEL
rkmath-0.2.9.dist-info/top_level.txt
rkmath-0.2.9.dist-info/RECORD
