Metadata-Version: 2.4
Name: rkmath
Version: 0.2.9
Summary: Math library for easy math operations
Author: Swifterhtmler
License-File: LICENSE
Requires-Dist: numpy>=1.21.0
Dynamic: author
Dynamic: description
Dynamic: description-content-type
Dynamic: license-file
Dynamic: requires-dist
Dynamic: summary
